context_probing/__init__.py
context_probing/core.py
context_probing/scripts/__init__.py
context_probing/scripts/conllu_to_hf.py
context_probing/scripts/predict_sliding.py
context_probing/scripts/preds_to_metrics.py
context_probing/unigram.py
context_probing/utils.py
context_probing-0.2.0.dist-info/LICENSE
context_probing-0.2.0.dist-info/METADATA
context_probing-0.2.0.dist-info/WHEEL
context_probing-0.2.0.dist-info/RECORD
