Metadata-Version: 2.1
Name: context-probing
Version: 0.2.0
Summary: 
Author: Ondřej Cífka
Author-email: cifkao@gmail.com
Requires-Python: >=3.9,<4.0
Classifier: Programming Language :: Python :: 3
Classifier: Programming Language :: Python :: 3.9
Classifier: Programming Language :: Python :: 3.10
Classifier: Programming Language :: Python :: 3.11
Requires-Dist: conllu (>=4.5.1,<5.0.0)
Requires-Dist: dask (>=2022.7.0,<2023.0.0)
Requires-Dist: datasets (>=2.3.2,<3.0.0)
Requires-Dist: ipython (>=8.4.0,<9.0.0)
Requires-Dist: jupyter (>=1.0.0,<2.0.0)
Requires-Dist: matplotlib (>=3.5.2,<4.0.0)
Requires-Dist: nopdb (>=0.2.0,<0.3.0)
Requires-Dist: pandas (>=1.4.3,<2.0.0)
Requires-Dist: seaborn (>=0.11.2,<0.12.0)
Requires-Dist: transformers[torch] (>=4.20.1,<5.0.0)
